Metadata-Version: 2.1
Name: branch-link
Version: 0.0.1
Summary: It is a peace of fullstack-mqtt project.
Home-page: https://github.com/phucbao9x/branch_link
Author: Phuc Bao
Author-email: nguyentranphucbao.working@gmail.com
